ldap_groups/__init__.py
ldap_groups/exceptions.py
ldap_groups/groups.py
ldap_groups/utils.py
ldap_groups-4.2.2.dist-info/DESCRIPTION.rst
ldap_groups-4.2.2.dist-info/METADATA
ldap_groups-4.2.2.dist-info/RECORD
ldap_groups-4.2.2.dist-info/WHEEL
ldap_groups-4.2.2.dist-info/metadata.json
ldap_groups-4.2.2.dist-info/top_level.txt
