Metadata-Version: 2.0
Name: ldap-groups
Version: 4.2.2
Summary: A python/django Active Directory group management abstraction that uses ldap3 as a backend for cross-platform compatibility.
Home-page: https://github.com/kavdev/ldap-groups/
Author: Alexander Kavanaugh
Author-email: alex@kavdev.io
License: License :: OSI Approved :: MIT License
Keywords: ldap active directory ldap-groups groups adgroups python django ad
Platform: UNKNOWN
Classifier: Development Status :: 5 - Production/Stable
Classifier: Environment :: Console
Classifier: Environment :: Web Environment
Classifier: Framework :: Django
Classifier: Intended Audience :: Developers
Classifier: Intended Audience :: System Administrators
Classifier: License :: OSI Approved :: MIT License
Classifier: Natural Language :: English
Classifier: Operating System :: OS Independent
Classifier: Programming Language :: Python :: 2.7
Classifier: Programming Language :: Python :: 3
Classifier: Programming Language :: Python :: 3.4
Classifier: Programming Language :: Python :: 3.5
Classifier: Topic :: Software Development :: Libraries :: Python Modules
Classifier: Topic :: System :: Systems Administration :: Authentication/Directory :: LDAP
Classifier: Topic :: Utilities
Requires-Dist: ldap3 (>=0.9.8.8)
